slash_slack/__init__.py
slash_slack/arg_functions.py
slash_slack/arg_types.py
slash_slack/blocks.py
slash_slack/exceptions.py
slash_slack/mock_slack.py
slash_slack/py.typed
slash_slack/signature_verifier.py
slash_slack/slash_slack.py
slash_slack/slash_slack_command.py
slash_slack/slash_slack_request.py
slash_slack-0.2.2.dist-info/LICENSE
slash_slack-0.2.2.dist-info/METADATA
slash_slack-0.2.2.dist-info/WHEEL
slash_slack-0.2.2.dist-info/entry_points.txt
slash_slack-0.2.2.dist-info/top_level.txt
slash_slack-0.2.2.dist-info/RECORD
