Metadata-Version: 2.1
Name: slash-slack
Version: 0.2.2
Summary: A python framework for slack slash bots.
Home-page: https://github.com/henryivesjones/slash-slack
Author-email: Henry Jones <henryivesjones@gmail.com>
License: GPL-3.0-or-later
Keywords: slack,fastapi,bot,slash command
Classifier: License :: OSI Approved :: GNU General Public License v3 or later (GPLv3+)
Classifier: Programming Language :: Python :: 3
Classifier: Programming Language :: Python :: 3.7
Classifier: Programming Language :: Python :: 3.8
Classifier: Programming Language :: Python :: 3.9
Classifier: Programming Language :: Python :: 3.10
Classifier: Programming Language :: Python :: 3.11
Requires-Python: >=3.6
License-File: LICENSE
Requires-Dist: aiohttp
Requires-Dist: fastapi
